tree_sitter_scss/__init__.pyi
tree_sitter_scss/binding.c
tree_sitter_scss/__init__.py
tree_sitter_scss/py.typed
tree_sitter_scss/_binding.abi3.so
tree_sitter_scss/queries/highlights.scm
tree_sitter_scss-1.0.0.dist-info/RECORD
tree_sitter_scss-1.0.0.dist-info/WHEEL
tree_sitter_scss-1.0.0.dist-info/top_level.txt
tree_sitter_scss-1.0.0.dist-info/METADATA
