Metadata-Version: 2.1
Name: tree-sitter-scss
Version: 1.0.0
Summary: SCSS grammar for tree-sitter
Author-email: Amaan Qureshi <amaanq12@gmail.com>
License: MIT
Project-URL: Homepage, https://github.com/tree-sitter-grammars/tree-sitter-scss
Keywords: incremental,parsing,tree-sitter,scss
Classifier: Intended Audience :: Developers
Classifier: License :: OSI Approved :: MIT License
Classifier: Topic :: Software Development :: Compilers
Classifier: Topic :: Text Processing :: Linguistic
Classifier: Typing :: Typed
Requires-Python: >=3.8
Provides-Extra: core
Requires-Dist: tree-sitter ~=0.21 ; extra == 'core'
